specctl/__init__.py
specctl/dc2k8s/README.md
specctl/dc2k8s/__init__.py
specctl/dc2k8s/dc_parser.py
specctl/dc2k8s/dc_reader_writer.py
specctl/ecs2k8s/README.md
specctl/ecs2k8s/__init__.py
specctl/ecs2k8s/ecs_parser.py
specctl/ecs2k8s/ecs_reader_writer.py
specctl/k8s2ecs/README.md
specctl/k8s2ecs/__init__.py
specctl/k8s2ecs/ecs_objects.py
specctl/k8s2ecs/ecs_output.py
specctl/k8s2ecs/ingress.py
specctl/k8s2ecs/k8s_parser.py
specctl/k8s2ecs/k8s_reader.py
specctl/k8s2ecs/tf_output.py
specctl/k8s_objects.py
specctl/quantity.py
specctl/specctl.py
specctl/utils.py
specctl-0.1.6.dist-info/LICENSE
specctl-0.1.6.dist-info/METADATA
specctl-0.1.6.dist-info/WHEEL
specctl-0.1.6.dist-info/entry_points.txt
specctl-0.1.6.dist-info/RECORD
