Metadata-Version: 2.1
Name: specctl
Version: 0.1.6
Summary: 
License: Apache 2.0
Author: Arvind Soni
Author-email: arvindsoni@gmail.com
Requires-Python: >=3.8,<4.0
Classifier: License :: Other/Proprietary License
Classifier: Programming Language :: Python :: 3
Classifier: Programming Language :: Python :: 3.8
Classifier: Programming Language :: Python :: 3.9
Classifier: Programming Language :: Python :: 3.10
Classifier: Programming Language :: Python :: 3.11
Requires-Dist: PyYAML (>=6.0,<7.0)
Requires-Dist: boto3 (>=1.26.130,<2.0.0)
Requires-Dist: click (>=8.1.3,<9.0.0)
Requires-Dist: kubernetes (>=26.1.0,<27.0.0)
Requires-Dist: pick (>=2.2.0,<3.0.0)
Requires-Dist: python-dotenv (>=1.0.0,<2.0.0)
